gpapi/__init__.py
gpapi/config.py
gpapi/device.properties
gpapi/googleplay.py
gpapi/googleplay_pb2.py
gpapi/utils.py
matlink_gpapi-0.4.4.5.dist-info/LICENSE.md
matlink_gpapi-0.4.4.5.dist-info/METADATA
matlink_gpapi-0.4.4.5.dist-info/WHEEL
matlink_gpapi-0.4.4.5.dist-info/top_level.txt
matlink_gpapi-0.4.4.5.dist-info/RECORD
